solstice/__init__.py
solstice/experiment.py
solstice/metrics.py
solstice/trainer.py
solstice/utils.py
solstice_jax-0.0.1.dist-info/LICENSE
solstice_jax-0.0.1.dist-info/WHEEL
solstice_jax-0.0.1.dist-info/METADATA
solstice_jax-0.0.1.dist-info/RECORD
