Metadata-Version: 2.1
Name: solstice-jax
Version: 0.0.1
Summary: Solstice, a library for creating and scaling experiments in JAX.
Home-page: https://github.com/Charl-AI/Solstice
License: MIT
Author: Charles Jones
Author-email: cj1917@ic.ac.uk
Requires-Python: >=3.7,<3.11
Classifier: Intended Audience :: Developers
Classifier: Intended Audience :: Information Technology
Classifier: Intended Audience :: Science/Research
Classifier: License :: OSI Approved :: MIT License
Classifier: Programming Language :: Python :: 3
Classifier: Programming Language :: Python :: 3.10
Classifier: Programming Language :: Python :: 3.7
Classifier: Programming Language :: Python :: 3.8
Classifier: Programming Language :: Python :: 3.9
Classifier: Topic :: Scientific/Engineering :: Artificial Intelligence
Requires-Dist: equinox (>=0.5.4,<0.6.0)
Requires-Dist: tqdm (>=4.64.0,<5.0.0)
Requires-Dist: typing-extensions (>=4.3.0,<5.0.0)
Project-URL: Documentation, https://charl-ai.github.io/Solstice/
Project-URL: Repository, https://github.com/Charl-AI/Solstice
